{
  "v": 1,
  "id": "i-m-that-somebody",
  "title": "I'm That Somebody",
  "artist": null,
  "generatedAt": "2026-07-09T18:11:32.697Z",
  "duration": 261.36,
  "style": {
    "styleSentence": "A glossy late-90s club track at 96 BPM featuring sparse syncopated drums with off-grid percussion clicks, a rubbery bassline, and bright chiptune/FM synth riffs that evoke classic blue-sky video game music, all anchored by smooth confident male vocals utilizing intimate spoken replies to create a stop-start rhythmic pocket.",
    "genre": "R&B",
    "subGenres": [
      "Hip-Hop Soul",
      "Nu-Disco",
      "Y2K Pop"
    ],
    "mood": "playful, confident, flirty, futuristic",
    "vocalStyle": "Smooth male lead with playful confidence mixed with intimate whispered ad-libs and staccato spoken interjections between sung phrases",
    "energy": "medium",
    "language": "English",
    "bpm": 96,
    "bpmExact": 95.7,
    "key": "F",
    "mode": "minor",
    "keyConfidence": 0.714,
    "palette": [
      "#080808",
      "#180808",
      "#281808",
      "#181808",
      "#280808"
    ]
  },
  "sections": [
    {
      "i": 0,
      "id": "i-m-that-somebody::intro::0",
      "kind": "intro",
      "ordinal": null,
      "voice": {
        "gender": null,
        "group": null,
        "spoken": null,
        "descriptor": "Whispered, playful"
      },
      "raw": "Intro - Whispered, playful",
      "text": "Yeah\nYou asked me a question\nI already had the answer\nListen",
      "lines": 4,
      "startT": 0.64,
      "endT": 11.2,
      "bars": 4
    },
    {
      "i": 1,
      "id": "i-m-that-somebody::verse-1::1",
      "kind": "verse",
      "ordinal": 1,
      "voice": {
        "gender": "male",
        "group": null,
        "spoken": null,
        "descriptor": "Smooth Male Vocal"
      },
      "raw": "Verse 1 - Smooth Male Vocal",
      "text": "You been moving cautious\nLike the room got eyes\nLike the walls might talk\nLike the night got spies\nI see how you look\nWhen the bassline drops\nHalf a smile on your face\nThen you tell me stop\nYou got secrets in your rhythm\nLittle warnings in your tone\nBut I’m not here to run it\nI’m here to bring it home",
      "lines": 12,
      "startT": 11.2,
      "endT": 29.44,
      "bars": 7
    },
    {
      "i": 2,
      "id": "i-m-that-somebody::prechorus::2",
      "kind": "prechorus",
      "ordinal": null,
      "voice": {
        "gender": null,
        "group": null,
        "spoken": true,
        "descriptor": "Sung then spoken"
      },
      "raw": "Pre-Chorus - Sung then spoken",
      "text": "Iiii wooon’t let thiiis shooow\n[Spoken] Won’t tell a soul, not anybody\nIiii knooow how thiiis goooes\n[Spoken] Keep it locked, keep it quiet, nobody\nIf you let me close\n[Spoken] I won’t make it public, no\nIf you let me know\n[Spoken] I won’t tell nobody\nI’m talking nobody",
      "lines": 9,
      "startT": 29.44,
      "endT": 46.08,
      "bars": 7
    },
    {
      "i": 3,
      "id": "i-m-that-somebody::hook::3",
      "kind": "hook",
      "ordinal": null,
      "voice": {
        "gender": null,
        "group": null,
        "spoken": true,
        "descriptor": "Catchy, same sung/spoken pattern"
      },
      "raw": "Hook - Catchy, same sung/spoken pattern",
      "text": "You al-rea-dy know\nYou said you need somebody\nI said I’ll be that somebody\nSay less, don’t say no\nYou don’t gotta need somebody\nI’m right here, I’m that somebody\nYou al-rea-dy know\nYou said you need somebody\nI said I’ll be that somebody\nSay less, don’t say no\nYou don’t gotta need somebody\nI’m right here, I’m that somebody",
      "lines": 12,
      "startT": 46.08,
      "endT": 74.4,
      "bars": 11
    },
    {
      "i": 4,
      "id": "i-m-that-somebody::hook::4",
      "kind": "hook",
      "ordinal": null,
      "voice": {
        "gender": null,
        "group": null,
        "spoken": null,
        "descriptor": "Vocal chops, playful"
      },
      "raw": "Post-Hook - Vocal chops, playful",
      "text": "That somebody\nThat somebody\nI’ll be that somebody\nNobody, nobody\nI won’t tell nobody",
      "lines": 5,
      "startT": 74.4,
      "endT": 86.89,
      "bars": 5
    },
    {
      "i": 5,
      "id": "i-m-that-somebody::verse-2::5",
      "kind": "verse",
      "ordinal": 2,
      "voice": {
        "gender": null,
        "group": null,
        "spoken": null,
        "descriptor": "Flirty, confident"
      },
      "raw": "Verse 2 - Flirty, confident",
      "text": "You asked if I’m steady\nGirl, you know I don’t fold\nI don’t move reckless\nI don’t speak what I’m told\nYou can test my patience\nYou can check my pride\nI’ll still keep your name\nOn the safer side\nYou don’t need a rumor\nYou don’t need a scene\nYou need somebody solid\nWhen the lights go green\nAnd if the world gets loud\nI’ll turn the noise down low\nPut your trust in my hands\nAnd I won’t let it go",
      "lines": 16,
      "startT": 86.89,
      "endT": 106.64,
      "bars": 8
    },
    {
      "i": 6,
      "id": "i-m-that-somebody::prechorus-2::6",
      "kind": "prechorus",
      "ordinal": 2,
      "voice": {
        "gender": null,
        "group": null,
        "spoken": true,
        "descriptor": "Direct response, sung then spoken"
      },
      "raw": "Pre-Chorus 2 - Direct response, sung then spoken",
      "text": "Youuu knooow I’m respooonsible\n[Spoken] You ain’t gotta watch your back when I’m beside you\nYouuu knooow I’m respooonsible\n[Spoken] I don’t need the spotlight just to hide you\nYou’re not just anybody\n[Spoken] That’s why I move different when I’m around you\nYou’re not just anybody\n[Spoken] I saw that from the first time I found you",
      "lines": 8,
      "startT": 106.64,
      "endT": 126.8,
      "bars": 8
    },
    {
      "i": 7,
      "id": "i-m-that-somebody::hook::7",
      "kind": "hook",
      "ordinal": null,
      "voice": {
        "gender": null,
        "group": null,
        "spoken": null,
        "descriptor": null
      },
      "raw": "Hook",
      "text": "You al-rea-dy know\nYou said you need somebody\nI said I’ll be that somebody\nSay less, don’t say no\nYou don’t gotta need somebody\nI’m right here, I’m that somebody\nYou al-rea-dy know\nYou said you need somebody\nI said I’ll be that somebody\nSay less, don’t say no\nYou don’t gotta need somebody\nI’m right here, I’m that somebody",
      "lines": 12,
      "startT": 126.8,
      "endT": 156.4,
      "bars": 12
    },
    {
      "i": 8,
      "id": "i-m-that-somebody::bridge::8",
      "kind": "bridge",
      "ordinal": null,
      "voice": {
        "gender": null,
        "group": null,
        "spoken": null,
        "descriptor": "Lower, more intimate"
      },
      "raw": "Bridge - Lower, more intimate",
      "text": "Sometimes you’re sweet, sweet\nSometimes you’re trouble, trouble\nSometimes you pull me close\nThen act like I said too much though\nI like it when you’re goody, goody\nI love it when you’re naughty, naughty\nEither way, you got me, got me\nI’m not leaving this party, party",
      "lines": 8,
      "startT": 156.4,
      "endT": 177.92,
      "bars": 9
    },
    {
      "i": 9,
      "id": "i-m-that-somebody::breakdown::9",
      "kind": "breakdown",
      "ordinal": null,
      "voice": {
        "gender": null,
        "group": null,
        "spoken": true,
        "descriptor": "Half sung, half spoken, highlight section"
      },
      "raw": "Breakdown - Half sung, half spoken, highlight section",
      "text": "Iiii wooon’t let thiiis gooo\n[Spoken] Won’t tell nobody, I’m talking nobody\nIf you let me know\n[Spoken] I won’t tell nobody, I’m talking nobody\nIf you let me close\n[Spoken] I’ll keep it between you and me\nIf you let this grow\n[Spoken] I’ll be exactly who I said I’d be\nIiii wooon’t let thiiis gooo\n[Spoken] Won’t tell nobody, I’m talking nobody\nIf you let me know\n[Spoken] I won’t tell nobody, I’m talking nobody",
      "lines": 12,
      "startT": 177.92,
      "endT": 209.76,
      "bars": 13
    },
    {
      "i": 10,
      "id": "i-m-that-somebody::hook::10",
      "kind": "hook",
      "ordinal": null,
      "voice": {
        "gender": null,
        "group": null,
        "spoken": null,
        "descriptor": "Bigger, more melodic"
      },
      "raw": "Final Hook - Bigger, more melodic",
      "text": "You al-rea-dy know\nYou said you need somebody\nI said I’ll be that somebody\nSay less, don’t say no\nYou don’t gotta need somebody\nI’m right here, I’m that somebody\nYou al-rea-dy know\nYou said you need somebody\nI said I’ll be that somebody\nSay less, don’t say no\nYou don’t gotta need somebody\nI’m right here, I’m that somebody",
      "lines": 12,
      "startT": 209.76,
      "endT": 236.8,
      "bars": 11
    },
    {
      "i": 11,
      "id": "i-m-that-somebody::outro::11",
      "kind": "outro",
      "ordinal": null,
      "voice": {
        "gender": null,
        "group": null,
        "spoken": null,
        "descriptor": "Whispered over quirky beat"
      },
      "raw": "Outro - Whispered over quirky beat",
      "text": "Nobody\nNobody\nI won’t tell nobody\nYou already know\nI’ll be that somebody",
      "lines": 5,
      "startT": 236.8,
      "endT": 261.36,
      "bars": 10
    }
  ],
  "signature": [
    {
      "word": "lights",
      "img": "https://pub-d3fd6ef07c3a4fc79ec69aa81645f904.r2.dev/lexicon/lights/s20-3-word-portrait.webp",
      "line": "You dont need a scene You need somebody solid When the lights go green And if the world gets loud Ill turn the noise down",
      "t": 101.123,
      "recipe": "3-word-portrait"
    },
    {
      "word": "move",
      "img": "https://pub-d3fd6ef07c3a4fc79ec69aa81645f904.r2.dev/lexicon/move/s5-1-word-portrait.webp",
      "line": "if Im steady Girl you know I dont fold I dont move reckless I dont speak what Im told You can test my patience You",
      "t": 90.291,
      "recipe": "1-word-portrait"
    },
    {
      "word": "night",
      "img": "https://pub-d3fd6ef07c3a4fc79ec69aa81645f904.r2.dev/lexicon/night/s8-3-word-portrait.webp",
      "line": "Like the room got eyes Like the walls might talk Like the night got spies I see how you look When the bassline",
      "t": 15.859,
      "recipe": "3-word-portrait"
    },
    {
      "word": "soul",
      "img": "https://pub-d3fd6ef07c3a4fc79ec69aa81645f904.r2.dev/lexicon/soul/s1-6-word-portrait.webp",
      "line": "Iiii wooont let thiiis shooow Spoken Wont tell a soul not anybody Iiii",
      "t": 31.29,
      "recipe": "6-word-portrait"
    },
    {
      "word": "rhythm",
      "img": "https://pub-d3fd6ef07c3a4fc79ec69aa81645f904.r2.dev/lexicon/rhythm/s6-2-poster.webp",
      "line": "Then you tell me stop You got secrets in your rhythm Little warnings in your tone But Im not here to run it Im",
      "t": 23.313,
      "recipe": "2-poster"
    },
    {
      "word": "different",
      "img": "https://pub-d3fd6ef07c3a4fc79ec69aa81645f904.r2.dev/lexicon/different/s6-2-word-portrait.webp",
      "line": "you Youre not just anybody Spoken Thats why I move different when Im around you Youre not",
      "t": 120.145,
      "recipe": "2-word-portrait"
    },
    {
      "word": "party",
      "img": "https://pub-d3fd6ef07c3a4fc79ec69aa81645f904.r2.dev/lexicon/party/s3-6-word-portrait.webp",
      "line": "way you got me got me Im not leaving this party party",
      "t": 174.324,
      "recipe": "6-word-portrait"
    },
    {
      "word": "love",
      "img": "https://pub-d3fd6ef07c3a4fc79ec69aa81645f904.r2.dev/lexicon/love/s16-2-stickers.webp",
      "line": "I like it when youre goody goody I love it when youre naughty naughty Either way you got",
      "t": 168.925,
      "recipe": "2-stickers"
    }
  ],
  "provides": [
    "breakdown",
    "bridge",
    "hook",
    "intro",
    "outro",
    "prechorus",
    "verse"
  ]
}